django_outbox_pattern/__init__.py
django_outbox_pattern/admin.py
django_outbox_pattern/apps.py
django_outbox_pattern/bases.py
django_outbox_pattern/choices.py
django_outbox_pattern/consumers.py
django_outbox_pattern/decorators.py
django_outbox_pattern/exceptions.py
django_outbox_pattern/factories.py
django_outbox_pattern/headers.py
django_outbox_pattern/listeners.py
django_outbox_pattern/management/__init__.py
django_outbox_pattern/management/commands/__init__.py
django_outbox_pattern/management/commands/publish.py
django_outbox_pattern/management/commands/subscribe.py
django_outbox_pattern/migrations/0001_initial.py
django_outbox_pattern/migrations/0002_received_msg_id.py
django_outbox_pattern/migrations/0003_alter_published_version.py
django_outbox_pattern/migrations/0004_auto_20230403_1637.py
django_outbox_pattern/migrations/0005_published_headers.py
django_outbox_pattern/migrations/0006_published_published_status_27c9ec_btree.py
django_outbox_pattern/migrations/__init__.py
django_outbox_pattern/models.py
django_outbox_pattern/payloads.py
django_outbox_pattern/producers.py
django_outbox_pattern/settings.py
django_outbox_pattern-3.0.7.dist-info/LICENSE
django_outbox_pattern-3.0.7.dist-info/METADATA
django_outbox_pattern-3.0.7.dist-info/WHEEL
django_outbox_pattern-3.0.7.dist-info/RECORD
