Metadata-Version: 2.1
Name: django-outbox-pattern
Version: 3.0.7
Summary: A django application to make it easier to use the transactional outbox pattern
Home-page: https://github.com/juntossomosmais/django-outbox-pattern
License: MIT
Keywords: transactional outbox patterns,application events,microservices
Author: Hugo Brilhante
Author-email: hugobrilhante@gmail.com
Requires-Python: >=3.10,<4.0
Classifier: Development Status :: 5 - Production/Stable
Classifier: Environment :: Web Environment
Classifier: Framework :: Django :: 5.0
Classifier: Framework :: Django :: 5.1
Classifier: Intended Audience :: Developers
Classifier: License :: OSI Approved :: MIT License
Classifier: Operating System :: OS Independent
Classifier: Programming Language :: Python
Classifier: Programming Language :: Python :: 3
Classifier: Programming Language :: Python :: 3.10
Classifier: Programming Language :: Python :: 3.11
Classifier: Programming Language :: Python :: 3.12
Classifier: Topic :: Internet :: WWW/HTTP
Classifier: Topic :: Internet :: WWW/HTTP :: Dynamic Content
Requires-Dist: django (>=5.0.8)
Requires-Dist: request-id-django-log (>=0.2.0,<0.3.0)
Requires-Dist: stomp.py (>=8.0.1,<9)
Project-URL: Documentation, https://github.com/juntossomosmais/django-outbox-pattern
Project-URL: Repository, https://github.com/juntossomosmais/django-outbox-pattern
